{
    "data": {
        "data_result": [
            {
                "flow_index": "",
                "hot_index": "",
                "is_addible": true,
                "key_point_list": [],
                "new_pay_amt": {
                    "value_range": [
                        {
                            "unit": "price",
                            "value": 750000
                        },
                        {
                            "unit": "price",
                            "value": 1000000
                        }
                    ]
                },
                "not_addible_reason": "",
                "product_click_cnt": {
                    "value_range": [
                        {
                            "unit": "number",
                            "value": 0
                        },
                        {
                            "unit": "number",
                            "value": 50
                        }
                    ]
                },
                "product_info": {
                    "brand_type": 0,
                    "category_id": 0,
                    "id": "3735152123327938872",
                    "image_url": "https://p3-aio.ecombdimg.com/obj/ecom-shop-material/KLwlqILV_m_7afe72d1092a2c26bfef505a34034594_sx_128879_www1000-1000",
                    "is_follow": false,
                    "leaf_category_id": 20588,
                    "name": "全国联通100元手机话费充值",
                    "newly_on_ranking": true,
                    "price_bin": "¥100-¥100",
                    "product_detail_h5_url": "https://haohuo.jinritemai.com/ecommerce/trade/detail/index.html?id=3735152123327938872\u0026origin_type=pc_compass_manage",
                    "rank": 81,
                    "rank_change": -70,
                    "second_category_id": 0,
                    "shop_list": [
                        {
                            "author_info": {
                                "author_id": "100746171065",
                                "author_logo": "https://p3.douyinpic.com/origin/aweme-avatar/tos-cn-avt-0015_2a7f650e0dec9053e460ced52f4bc450",
                                "author_nick_name": "沙漠之星网络专营店",
                                "aweme_id": "1669286996",
                                "fans_count": 0,
                                "url_list": [
                                    "https://p3.douyinpic.com/img/aweme-qrcode/AXOYzR7471169927890716454~c5_720x720.webp?from=3252049127",
                                    "https://p11.douyinpic.com/img/aweme-qrcode/AXOYzR7471169927890716454~c5_720x720.webp?from=3252049127",
                                    "https://p26.douyinpic.com/img/aweme-qrcode/AXOYzR7471169927890716454~c5_720x720.webp?from=3252049127",
                                    "https://p3.douyinpic.com/img/aweme-qrcode/AXOYzR7471169927890716454~c5_720x720.jpeg?from=3252049127"
                                ]
                            },
                            "image": "https://p6-ecom-qualification-sign.ecombdimg.com/tos-cn-i-6vegkygxbk/09c79715cfef42a1b31b26f6b4a50904~tplv-6vegkygxbk-s:750.image?lk3s=c08c0450\u0026x-expires=1771055234\u0026x-signature=4X7ms8YPWHmh7nfOtEx2muRsoyE%3D",
                            "shop_id": "42957553",
                            "shop_name": "沙漠之星网络专营店"
                        }
                    ],
                    "spu_id": "",
                    "third_category_id": 0,
                    "uri": "",
                    "url_list": [
                        "https://p11.douyinpic.com/img/aweme-qrcode/LBfrvN7471179099076069120~c5_720x720.webp?from=2634875926",
                        "https://p26.douyinpic.com/img/aweme-qrcode/LBfrvN7471179099076069120~c5_720x720.webp?from=2634875926",
                        "https://p3.douyinpic.com/img/aweme-qrcode/LBfrvN7471179099076069120~c5_720x720.webp?from=2634875926",
                        "https://p11.douyinpic.com/img/aweme-qrcode/LBfrvN7471179099076069120~c5_720x720.jpeg?from=2634875926"
                    ]
                },
                "trade_index": ""
            },
            {
                "flow_index": "",
                "hot_index": "",
                "is_addible": true,
                "key_point_list": [],
                "new_pay_amt": {
                    "value_range": [
                        {
                            "unit": "price",
                            "value": 750000
                        },
                        {
                            "unit": "price",
                            "value": 1000000
                        }
                    ]
                },
                "not_addible_reason": "",
                "product_click_cnt": {
                    "value_range": [
                        {
                            "unit": "number",
                            "value": 0
                        },
                        {
                            "unit": "number",
                            "value": 50
                        }
                    ]
                },
                "product_info": {
                    "brand_type": 0,
                    "category_id": 0,
                    "id": "3725765841820713064",
                    "image_url": "https://p3-aio.ecombdimg.com/obj/ecom-shop-material/CxULgQNE_m_a038411795b32522fdd88f42c5d57526_sx_156149_www800-800",
                    "is_follow": false,
                    "leaf_category_id": 20588,
                    "name": "C辽宁联通100元话费充值",
                    "newly_on_ranking": false,
                    "price_bin": "¥100-¥100",
                    "product_detail_h5_url": "https://haohuo.jinritemai.com/ecommerce/trade/detail/index.html?id=3725765841820713064\u0026origin_type=pc_compass_manage",
                    "rank": 82,
                    "rank_change": 19,
                    "second_category_id": 0,
                    "shop_list": [
                        {
                            "author_info": {
                                "author_id": "103987957403",
                                "author_logo": "https://p3.douyinpic.com/origin/aweme-avatar/tos-cn-i-0813_acd387affdcf4772a64910c67fb7fee5",
                                "author_nick_name": "杭州手拉手话费店",
                                "aweme_id": "45025609566",
                                "fans_count": 0,
                                "url_list": [
                                    "https://p3.douyinpic.com/img/aweme-qrcode/FVHZkb7471177667677538102~c5_720x720.webp?from=3252049127",
                                    "https://p11.douyinpic.com/img/aweme-qrcode/FVHZkb7471177667677538102~c5_720x720.webp?from=3252049127",
                                    "https://p26.douyinpic.com/img/aweme-qrcode/FVHZkb7471177667677538102~c5_720x720.webp?from=3252049127",
                                    "https://p3.douyinpic.com/img/aweme-qrcode/FVHZkb7471177667677538102~c5_720x720.jpeg?from=3252049127"
                                ]
                            },
                            "image": "https://p3-ecom-qualification-sign.ecombdimg.com/tos-cn-i-6vegkygxbk/6bdcde68e8de4260aff332d7789b2c1d~tplv-6vegkygxbk-s:750.image?lk3s=c08c0450\u0026x-expires=1771054733\u0026x-signature=iB9N0h0GMxFmcIVFzW0T2N9ZSwM%3D",
                            "shop_id": "8071032",
                            "shop_name": "杭州手拉手话费店"
                        }
                    ],
                    "spu_id": "",
                    "third_category_id": 0,
                    "uri": "",
                    "url_list": [
                        "https://p11.douyinpic.com/img/aweme-qrcode/kVvHhc7471170923127768844~c5_720x720.webp?from=2634875926",
                        "https://p26.douyinpic.com/img/aweme-qrcode/kVvHhc7471170923127768844~c5_720x720.webp?from=2634875926",
                        "https://p3.douyinpic.com/img/aweme-qrcode/kVvHhc7471170923127768844~c5_720x720.webp?from=2634875926",
                        "https://p11.douyinpic.com/img/aweme-qrcode/kVvHhc7471170923127768844~c5_720x720.jpeg?from=2634875926"
                    ]
                },
                "trade_index": ""
            },
            {
                "flow_index": "",
                "hot_index": "",
                "is_addible": true,
                "key_point_list": [],
                "new_pay_amt": {
                    "value_range": [
                        {
                            "unit": "price",
                            "value": 750000
                        },
                        {
                            "unit": "price",
                            "value": 1000000
                        }
                    ]
                },
                "not_addible_reason": "",
                "product_click_cnt": {
                    "value_range": [
                        {
                            "unit": "number",
                            "value": 0
                        },
                        {
                            "unit": "number",
                            "value": 50
                        }
                    ]
                },
                "product_info": {
                    "brand_type": 0,
                    "category_id": 0,
                    "id": "3725762012907700700",
                    "image_url": "https://p9-aio.ecombdimg.com/obj/ecom-shop-material/CxULgQNE_m_e1e95387f5f6057f90fe4b9ce10ebb46_sx_152095_www800-800",
                    "is_follow": false,
                    "leaf_category_id": 20588,
                    "name": "C山西联通100元话费充值",
                    "newly_on_ranking": false,
                    "price_bin": "¥100-¥100",
                    "product_detail_h5_url": "https://haohuo.jinritemai.com/ecommerce/trade/detail/index.html?id=3725762012907700700\u0026origin_type=pc_compass_manage",
                    "rank": 83,
                    "rank_change": -4,
                    "second_category_id": 0,
                    "shop_list": [
                        {
                            "author_info": {
                                "author_id": "103987957403",
                                "author_logo": "https://p3.douyinpic.com/origin/aweme-avatar/tos-cn-i-0813_acd387affdcf4772a64910c67fb7fee5",
                                "author_nick_name": "杭州手拉手话费店",
                                "aweme_id": "45025609566",
                                "fans_count": 0,
                                "url_list": [
                                    "https://p3.douyinpic.com/img/aweme-qrcode/FVHZkb7471177667677538102~c5_720x720.webp?from=3252049127",
                                    "https://p11.douyinpic.com/img/aweme-qrcode/FVHZkb7471177667677538102~c5_720x720.webp?from=3252049127",
                                    "https://p26.douyinpic.com/img/aweme-qrcode/FVHZkb7471177667677538102~c5_720x720.webp?from=3252049127",
                                    "https://p3.douyinpic.com/img/aweme-qrcode/FVHZkb7471177667677538102~c5_720x720.jpeg?from=3252049127"
                                ]
                            },
                            "image": "https://p3-ecom-qualification-sign.ecombdimg.com/tos-cn-i-6vegkygxbk/6bdcde68e8de4260aff332d7789b2c1d~tplv-6vegkygxbk-s:750.image?lk3s=c08c0450\u0026x-expires=1771054733\u0026x-signature=iB9N0h0GMxFmcIVFzW0T2N9ZSwM%3D",
                            "shop_id": "8071032",
                            "shop_name": "杭州手拉手话费店"
                        }
                    ],
                    "spu_id": "",
                    "third_category_id": 0,
                    "uri": "",
                    "url_list": [
                        "https://p11.douyinpic.com/img/aweme-qrcode/RMcNSf7471170932388742966~c5_720x720.webp?from=2634875926",
                        "https://p26.douyinpic.com/img/aweme-qrcode/RMcNSf7471170932388742966~c5_720x720.webp?from=2634875926",
                        "https://p3.douyinpic.com/img/aweme-qrcode/RMcNSf7471170932388742966~c5_720x720.webp?from=2634875926",
                        "https://p11.douyinpic.com/img/aweme-qrcode/RMcNSf7471170932388742966~c5_720x720.jpeg?from=2634875926"
                    ]
                },
                "trade_index": ""
            },
            {
                "flow_index": "",
                "hot_index": "",
                "is_addible": true,
                "key_point_list": [],
                "new_pay_amt": {
                    "value_range": [
                        {
                            "unit": "price",
                            "value": 750000
                        },
                        {
                            "unit": "price",
                            "value": 1000000
                        }
                    ]
                },
                "not_addible_reason": "",
                "product_click_cnt": {
                    "value_range": [
                        {
                            "unit": "number",
                            "value": 0
                        },
                        {
                            "unit": "number",
                            "value": 50
                        }
                    ]
                },
                "product_info": {
                    "brand_type": 0,
                    "category_id": 0,
                    "id": "3691988151095656811",
                    "image_url": "https://p3-aio.ecombdimg.com/obj/ecom-shop-material/ZKozisQb_m_a15d3bb9b9ff6b4c032317cbe7aa8418_sx_91380_www800-800",
                    "is_follow": false,
                    "leaf_category_id": 20588,
                    "name": "充值中心联通100重庆联通话费充值100元",
                    "newly_on_ranking": true,
                    "price_bin": "¥100-¥100",
                    "product_detail_h5_url": "https://haohuo.jinritemai.com/ecommerce/trade/detail/index.html?id=3691988151095656811\u0026origin_type=pc_compass_manage",
                    "rank": 84,
                    "rank_change": 29,
                    "second_category_id": 0,
                    "shop_list": [
                        {
                            "author_info": {
                                "author_id": "0",
                                "author_logo": "",
                                "author_nick_name": "",
                                "aweme_id": "",
                                "fans_count": 0,
                                "url_list": []
                            },
                            "image": "https://p6-ecom-qualification-sign.ecombdimg.com/tos-cn-i-6vegkygxbk/b26f6fb030f045dfb8735deba2788105~tplv-6vegkygxbk-s:750.image?lk3s=c08c0450\u0026x-expires=1771054022\u0026x-signature=VVy6rPR0Dl4v7phM2T9xRz9A3cM%3D",
                            "shop_id": "170065964",
                            "shop_name": "合创比特话费充值"
                        }
                    ],
                    "spu_id": "",
                    "third_category_id": 0,
                    "uri": "",
                    "url_list": [
                        "https://p11.douyinpic.com/img/aweme-qrcode/NmnBZA7471170982212896539~c5_720x720.webp?from=2634875926",
                        "https://p3.douyinpic.com/img/aweme-qrcode/NmnBZA7471170982212896539~c5_720x720.webp?from=2634875926",
                        "https://p26.douyinpic.com/img/aweme-qrcode/NmnBZA7471170982212896539~c5_720x720.webp?from=2634875926",
                        "https://p11.douyinpic.com/img/aweme-qrcode/NmnBZA7471170982212896539~c5_720x720.jpeg?from=2634875926"
                    ]
                },
                "trade_index": ""
            },
            {
                "flow_index": "",
                "hot_index": "",
                "is_addible": true,
                "key_point_list": [],
                "new_pay_amt": {
                    "value_range": [
                        {
                            "unit": "price",
                            "value": 750000
                        },
                        {
                            "unit": "price",
                            "value": 1000000
                        }
                    ]
                },
                "not_addible_reason": "",
                "product_click_cnt": {
                    "value_range": [
                        {
                            "unit": "number",
                            "value": 0
                        },
                        {
                            "unit": "number",
                            "value": 50
                        }
                    ]
                },
                "product_info": {
                    "brand_type": 0,
                    "category_id": 0,
                    "id": "3725773216355057977",
                    "image_url": "https://p3-aio.ecombdimg.com/obj/ecom-shop-material/CxULgQNE_m_d9fea948efd37d50e9dcadf420051a42_sx_156497_www800-800",
                    "is_follow": false,
                    "leaf_category_id": 20588,
                    "name": "C湖南联通100元话费充值",
                    "newly_on_ranking": false,
                    "price_bin": "¥100-¥100",
                    "product_detail_h5_url": "https://haohuo.jinritemai.com/ecommerce/trade/detail/index.html?id=3725773216355057977\u0026origin_type=pc_compass_manage",
                    "rank": 85,
                    "rank_change": -17,
                    "second_category_id": 0,
                    "shop_list": [
                        {
                            "author_info": {
                                "author_id": "103987957403",
                                "author_logo": "https://p3.douyinpic.com/origin/aweme-avatar/tos-cn-i-0813_acd387affdcf4772a64910c67fb7fee5",
                                "author_nick_name": "杭州手拉手话费店",
                                "aweme_id": "45025609566",
                                "fans_count": 0,
                                "url_list": [
                                    "https://p3.douyinpic.com/img/aweme-qrcode/FVHZkb7471177667677538102~c5_720x720.webp?from=3252049127",
                                    "https://p11.douyinpic.com/img/aweme-qrcode/FVHZkb7471177667677538102~c5_720x720.webp?from=3252049127",
                                    "https://p26.douyinpic.com/img/aweme-qrcode/FVHZkb7471177667677538102~c5_720x720.webp?from=3252049127",
                                    "https://p3.douyinpic.com/img/aweme-qrcode/FVHZkb7471177667677538102~c5_720x720.jpeg?from=3252049127"
                                ]
                            },
                            "image": "https://p3-ecom-qualification-sign.ecombdimg.com/tos-cn-i-6vegkygxbk/6bdcde68e8de4260aff332d7789b2c1d~tplv-6vegkygxbk-s:750.image?lk3s=c08c0450\u0026x-expires=1771054733\u0026x-signature=iB9N0h0GMxFmcIVFzW0T2N9ZSwM%3D",
                            "shop_id": "8071032",
                            "shop_name": "杭州手拉手话费店"
                        }
                    ],
                    "spu_id": "",
                    "third_category_id": 0,
                    "uri": "",
                    "url_list": [
                        "https://p11.douyinpic.com/img/aweme-qrcode/SOKUYS7471170932019660594~c5_720x720.webp?from=2634875926",
                        "https://p3.douyinpic.com/img/aweme-qrcode/SOKUYS7471170932019660594~c5_720x720.webp?from=2634875926",
                        "https://p26.douyinpic.com/img/aweme-qrcode/SOKUYS7471170932019660594~c5_720x720.webp?from=2634875926",
                        "https://p11.douyinpic.com/img/aweme-qrcode/SOKUYS7471170932019660594~c5_720x720.jpeg?from=2634875926"
                    ]
                },
                "trade_index": ""
            },
            {
                "flow_index": "",
                "hot_index": "",
                "is_addible": true,
                "key_point_list": [],
                "new_pay_amt": {
                    "value_range": [
                        {
                            "unit": "price",
                            "value": 750000
                        },
                        {
                            "unit": "price",
                            "value": 1000000
                        }
                    ]
                },
                "not_addible_reason": "",
                "product_click_cnt": {
                    "value_range": [
                        {
                            "unit": "number",
                            "value": 0
                        },
                        {
                            "unit": "number",
                            "value": 50
                        }
                    ]
                },
                "product_info": {
                    "brand_type": 0,
                    "category_id": 0,
                    "id": "3723485409607549426",
                    "image_url": "https://p3-aio.ecombdimg.com/obj/ecom-shop-material/aeGaTVed_m_6e34da18922806dcfd4a2ee6487ad4c3_sx_287796_www600-600",
                    "is_follow": false,
                    "leaf_category_id": 20588,
                    "name": " [ 充值中心] 内蒙联通话费充值100元（0-3小时充值）",
                    "newly_on_ranking": true,
                    "price_bin": "¥100-¥100",
                    "product_detail_h5_url": "https://haohuo.jinritemai.com/ecommerce/trade/detail/index.html?id=3723485409607549426\u0026origin_type=pc_compass_manage",
                    "rank": 86,
                    "second_category_id": 0,
                    "shop_list": [
                        {
                            "author_info": {
                                "author_id": "105354598080",
                                "author_logo": "https://p3.douyinpic.com/origin/aweme-avatar/tos-cn-avt-0015_8557d4d6001730d48cdcbef95348ba96",
                                "author_nick_name": "腾嘉话费充值专营店",
                                "aweme_id": "1821160475",
                                "fans_count": 0,
                                "url_list": [
                                    "https://p26.douyinpic.com/img/aweme-qrcode/zvzcDj7471168960516409088~c5_720x720.webp?from=3252049127",
                                    "https://p3.douyinpic.com/img/aweme-qrcode/zvzcDj7471168960516409088~c5_720x720.webp?from=3252049127",
                                    "https://p11.douyinpic.com/img/aweme-qrcode/zvzcDj7471168960516409088~c5_720x720.webp?from=3252049127",
                                    "https://p26.douyinpic.com/img/aweme-qrcode/zvzcDj7471168960516409088~c5_720x720.jpeg?from=3252049127"
                                ]
                            },
                            "image": "https://p3-ecom-qualification-sign.ecombdimg.com/tos-cn-i-6vegkygxbk/2749e43fafb443dd9581b9d334b6bf63~tplv-6vegkygxbk-s:750.image?lk3s=c08c0450\u0026x-expires=1771052842\u0026x-signature=XkEFvYJlK9UOnO5PfzPRehV%2FxdM%3D",
                            "shop_id": "60810691",
                            "shop_name": "腾嘉话费充值专营店"
                        }
                    ],
                    "spu_id": "",
                    "third_category_id": 0,
                    "uri": "",
                    "url_list": [
                        "https://p26.douyinpic.com/img/aweme-qrcode/AFJakm7471179106609022760~c5_720x720.webp?from=2634875926",
                        "https://p11.douyinpic.com/img/aweme-qrcode/AFJakm7471179106609022760~c5_720x720.webp?from=2634875926",
                        "https://p3.douyinpic.com/img/aweme-qrcode/AFJakm7471179106609022760~c5_720x720.webp?from=2634875926",
                        "https://p26.douyinpic.com/img/aweme-qrcode/AFJakm7471179106609022760~c5_720x720.jpeg?from=2634875926"
                    ]
                },
                "trade_index": ""
            },
            {
                "flow_index": "",
                "hot_index": "",
                "is_addible": true,
                "key_point_list": [],
                "new_pay_amt": {
                    "value_range": [
                        {
                            "unit": "price",
                            "value": 750000
                        },
                        {
                            "unit": "price",
                            "value": 1000000
                        }
                    ]
                },
                "not_addible_reason": "",
                "product_click_cnt": {
                    "value_range": [
                        {
                            "unit": "number",
                            "value": 0
                        },
                        {
                            "unit": "number",
                            "value": 50
                        }
                    ]
                },
                "product_info": {
                    "brand_type": 0,
                    "category_id": 0,
                    "id": "3462285138677883074",
                    "image_url": "https://p3-aio.ecombdimg.com/obj/ecom-shop-material/uvimjSDU_m_afee535862f962acfaf30ebe0a925ad9_sx_258638_www800-800",
                    "is_follow": false,
                    "leaf_category_id": 20588,
                    "name": "江苏联通100元手机话费充值",
                    "newly_on_ranking": false,
                    "price_bin": "¥100-¥100",
                    "product_detail_h5_url": "https://haohuo.jinritemai.com/ecommerce/trade/detail/index.html?id=3462285138677883074\u0026origin_type=pc_compass_manage",
                    "rank": 87,
                    "rank_change": 58,
                    "second_category_id": 0,
                    "shop_list": [
                        {
                            "author_info": {
                                "author_id": "4020256126017727",
                                "author_logo": "https://p3.douyinpic.com/origin/aweme-avatar/douyin-user-image-file_590fe90b25beb617cbe3eb78908034a6",
                                "author_nick_name": "千行你我充值专营店",
                                "aweme_id": "66110592546",
                                "fans_count": 0,
                                "url_list": [
                                    "https://p11.douyinpic.com/img/aweme-qrcode/VOpZKP7471174645891254050~c5_720x720.webp?from=3252049127",
                                    "https://p26.douyinpic.com/img/aweme-qrcode/VOpZKP7471174645891254050~c5_720x720.webp?from=3252049127",
                                    "https://p3.douyinpic.com/img/aweme-qrcode/VOpZKP7471174645891254050~c5_720x720.webp?from=3252049127",
                                    "https://p11.douyinpic.com/img/aweme-qrcode/VOpZKP7471174645891254050~c5_720x720.jpeg?from=3252049127"
                                ]
                            },
                            "image": "https://p3-ecom-qualification-sign.ecombdimg.com/temai/16002228492d1e3cc9c7c945372349c4cad3031e46bf62d414~tplv-6vegkygxbk-s:750.image?lk3s=c08c0450\u0026x-expires=1771055367\u0026x-signature=T5HIFpeeL%2F0060gFNl9uOB4HKfY%3D",
                            "shop_id": "8683547",
                            "shop_name": "千行你我充值专营店"
                        }
                    ],
                    "spu_id": "",
                    "third_category_id": 0,
                    "uri": "",
                    "url_list": [
                        "https://p3.douyinpic.com/img/aweme-qrcode/bNbooe7471170937220531977~c5_720x720.webp?from=2634875926",
                        "https://p26.douyinpic.com/img/aweme-qrcode/bNbooe7471170937220531977~c5_720x720.webp?from=2634875926",
                        "https://p11.douyinpic.com/img/aweme-qrcode/bNbooe7471170937220531977~c5_720x720.webp?from=2634875926",
                        "https://p3.douyinpic.com/img/aweme-qrcode/bNbooe7471170937220531977~c5_720x720.jpeg?from=2634875926"
                    ]
                },
                "trade_index": ""
            },
            {
                "flow_index": "",
                "hot_index": "",
                "is_addible": true,
                "key_point_list": [],
                "new_pay_amt": {
                    "value_range": [
                        {
                            "unit": "price",
                            "value": 750000
                        },
                        {
                            "unit": "price",
                            "value": 1000000
                        }
                    ]
                },
                "not_addible_reason": "",
                "product_click_cnt": {
                    "value_range": [
                        {
                            "unit": "number",
                            "value": 0
                        },
                        {
                            "unit": "number",
                            "value": 50
                        }
                    ]
                },
                "product_info": {
                    "brand_type": 0,
                    "category_id": 0,
                    "id": "3726146704555245810",
                    "image_url": "https://p9-aio.ecombdimg.com/obj/ecom-shop-material/png_m_d727dab9c05eb6992612c2186fc8b176_sx_581768_www1080-1080",
                    "is_follow": false,
                    "leaf_category_id": 20588,
                    "name": "【官方充值】河南联通100元快充话费",
                    "newly_on_ranking": false,
                    "price_bin": "¥100-¥100",
                    "product_detail_h5_url": "https://haohuo.jinritemai.com/ecommerce/trade/detail/index.html?id=3726146704555245810\u0026origin_type=pc_compass_manage",
                    "rank": 88,
                    "rank_change": -19,
                    "second_category_id": 0,
                    "shop_list": [
                        {
                            "author_info": {
                                "author_id": "4209375350628039",
                                "author_logo": "https://p3.douyinpic.com/origin/aweme-avatar/tos-cn-i-0813c001_oIkTDfzOeAAsIIA17MhEExCAmAtgOKAvpytgsB",
                                "author_nick_name": "昌盛话费快充店运营",
                                "aweme_id": "70512133243",
                                "fans_count": 0,
                                "url_list": [
                                    "https://p11.douyinpic.com/img/aweme-qrcode/WmIbhs7471174645081753382~c5_720x720.webp?from=3252049127",
                                    "https://p3.douyinpic.com/img/aweme-qrcode/WmIbhs7471174645081753382~c5_720x720.webp?from=3252049127",
                                    "https://p26.douyinpic.com/img/aweme-qrcode/WmIbhs7471174645081753382~c5_720x720.webp?from=3252049127",
                                    "https://p11.douyinpic.com/img/aweme-qrcode/WmIbhs7471174645081753382~c5_720x720.jpeg?from=3252049127"
                                ]
                            },
                            "image": "https://p3-ecom-qualification-sign.ecombdimg.com/tos-cn-i-6vegkygxbk/f4173a85154d4f1392af12f5e34e9bb6~tplv-6vegkygxbk-s:750.image?lk3s=c08c0450\u0026x-expires=1771051960\u0026x-signature=kF1J3oI0gjUEMpd94lLxWAiUFfc%3D",
                            "shop_id": "127635646",
                            "shop_name": "昌盛话费快充店"
                        }
                    ],
                    "spu_id": "",
                    "third_category_id": 0,
                    "uri": "",
                    "url_list": [
                        "https://p11.douyinpic.com/img/aweme-qrcode/pjaggm7471170942513743628~c5_720x720.webp?from=2634875926",
                        "https://p3.douyinpic.com/img/aweme-qrcode/pjaggm7471170942513743628~c5_720x720.webp?from=2634875926",
                        "https://p26.douyinpic.com/img/aweme-qrcode/pjaggm7471170942513743628~c5_720x720.webp?from=2634875926",
                        "https://p11.douyinpic.com/img/aweme-qrcode/pjaggm7471170942513743628~c5_720x720.jpeg?from=2634875926"
                    ]
                },
                "trade_index": ""
            },
            {
                "flow_index": "",
                "hot_index": "",
                "is_addible": true,
                "key_point_list": [],
                "new_pay_amt": {
                    "value_range": [
                        {
                            "unit": "price",
                            "value": 750000
                        },
                        {
                            "unit": "price",
                            "value": 1000000
                        }
                    ]
                },
                "not_addible_reason": "",
                "product_click_cnt": {
                    "value_range": [
                        {
                            "unit": "number",
                            "value": 0
                        },
                        {
                            "unit": "number",
                            "value": 50
                        }
                    ]
                },
                "product_info": {
                    "brand_type": 0,
                    "category_id": 0,
                    "id": "3723487279981920322",
                    "image_url": "https://p3-aio.ecombdimg.com/obj/ecom-shop-material/aeGaTVed_m_6e34da18922806dcfd4a2ee6487ad4c3_sx_287796_www600-600",
                    "is_follow": false,
                    "leaf_category_id": 20588,
                    "name": "[ 充值中心] 湖北联通话费充值100元（0-3小时充值）",
                    "newly_on_ranking": true,
                    "price_bin": "¥100-¥100",
                    "product_detail_h5_url": "https://haohuo.jinritemai.com/ecommerce/trade/detail/index.html?id=3723487279981920322\u0026origin_type=pc_compass_manage",
                    "rank": 89,
                    "second_category_id": 0,
                    "shop_list": [
                        {
                            "author_info": {
                                "author_id": "105354598080",
                                "author_logo": "https://p3.douyinpic.com/origin/aweme-avatar/tos-cn-avt-0015_8557d4d6001730d48cdcbef95348ba96",
                                "author_nick_name": "腾嘉话费充值专营店",
                                "aweme_id": "1821160475",
                                "fans_count": 0,
                                "url_list": [
                                    "https://p26.douyinpic.com/img/aweme-qrcode/zvzcDj7471168960516409088~c5_720x720.webp?from=3252049127",
                                    "https://p3.douyinpic.com/img/aweme-qrcode/zvzcDj7471168960516409088~c5_720x720.webp?from=3252049127",
                                    "https://p11.douyinpic.com/img/aweme-qrcode/zvzcDj7471168960516409088~c5_720x720.webp?from=3252049127",
                                    "https://p26.douyinpic.com/img/aweme-qrcode/zvzcDj7471168960516409088~c5_720x720.jpeg?from=3252049127"
                                ]
                            },
                            "image": "https://p3-ecom-qualification-sign.ecombdimg.com/tos-cn-i-6vegkygxbk/2749e43fafb443dd9581b9d334b6bf63~tplv-6vegkygxbk-s:750.image?lk3s=c08c0450\u0026x-expires=1771052842\u0026x-signature=XkEFvYJlK9UOnO5PfzPRehV%2FxdM%3D",
                            "shop_id": "60810691",
                            "shop_name": "腾嘉话费充值专营店"
                        }
                    ],
                    "spu_id": "",
                    "third_category_id": 0,
                    "uri": "",
                    "url_list": [
                        "https://p11.douyinpic.com/img/aweme-qrcode/IytVIF7471179097436063523~c5_720x720.webp?from=2634875926",
                        "https://p26.douyinpic.com/img/aweme-qrcode/IytVIF7471179097436063523~c5_720x720.webp?from=2634875926",
                        "https://p3.douyinpic.com/img/aweme-qrcode/IytVIF7471179097436063523~c5_720x720.webp?from=2634875926",
                        "https://p11.douyinpic.com/img/aweme-qrcode/IytVIF7471179097436063523~c5_720x720.jpeg?from=2634875926"
                    ]
                },
                "trade_index": ""
            },
            {
                "flow_index": "",
                "hot_index": "",
                "is_addible": true,
                "key_point_list": [],
                "new_pay_amt": {
                    "value_range": [
                        {
                            "unit": "price",
                            "value": 750000
                        },
                        {
                            "unit": "price",
                            "value": 1000000
                        }
                    ]
                },
                "not_addible_reason": "",
                "product_click_cnt": {
                    "value_range": [
                        {
                            "unit": "number",
                            "value": 0
                        },
                        {
                            "unit": "number",
                            "value": 50
                        }
                    ]
                },
                "product_info": {
                    "brand_type": 0,
                    "category_id": 0,
                    "id": "3725767087403171867",
                    "image_url": "https://p3-aio.ecombdimg.com/obj/ecom-shop-material/CxULgQNE_m_ec3036c0739f965d4d157793bc99c091_sx_156661_www800-800",
                    "is_follow": false,
                    "leaf_category_id": 20588,
                    "name": "C江苏联通100元话费充值",
                    "newly_on_ranking": false,
                    "price_bin": "¥100-¥100",
                    "product_detail_h5_url": "https://haohuo.jinritemai.com/ecommerce/trade/detail/index.html?id=3725767087403171867\u0026origin_type=pc_compass_manage",
                    "rank": 90,
                    "rank_change": 7,
                    "second_category_id": 0,
                    "shop_list": [
                        {
                            "author_info": {
                                "author_id": "103987957403",
                                "author_logo": "https://p3.douyinpic.com/origin/aweme-avatar/tos-cn-i-0813_acd387affdcf4772a64910c67fb7fee5",
                                "author_nick_name": "杭州手拉手话费店",
                                "aweme_id": "45025609566",
                                "fans_count": 0,
                                "url_list": [
                                    "https://p3.douyinpic.com/img/aweme-qrcode/FVHZkb7471177667677538102~c5_720x720.webp?from=3252049127",
                                    "https://p11.douyinpic.com/img/aweme-qrcode/FVHZkb7471177667677538102~c5_720x720.webp?from=3252049127",
                                    "https://p26.douyinpic.com/img/aweme-qrcode/FVHZkb7471177667677538102~c5_720x720.webp?from=3252049127",
                                    "https://p3.douyinpic.com/img/aweme-qrcode/FVHZkb7471177667677538102~c5_720x720.jpeg?from=3252049127"
                                ]
                            },
                            "image": "https://p3-ecom-qualification-sign.ecombdimg.com/tos-cn-i-6vegkygxbk/6bdcde68e8de4260aff332d7789b2c1d~tplv-6vegkygxbk-s:750.image?lk3s=c08c0450\u0026x-expires=1771054733\u0026x-signature=iB9N0h0GMxFmcIVFzW0T2N9ZSwM%3D",
                            "shop_id": "8071032",
                            "shop_name": "杭州手拉手话费店"
                        }
                    ],
                    "spu_id": "",
                    "third_category_id": 0,
                    "uri": "",
                    "url_list": [
                        "https://p3.douyinpic.com/img/aweme-qrcode/BlsHiO7471170927577843510~c5_720x720.webp?from=2634875926",
                        "https://p11.douyinpic.com/img/aweme-qrcode/BlsHiO7471170927577843510~c5_720x720.webp?from=2634875926",
                        "https://p26.douyinpic.com/img/aweme-qrcode/BlsHiO7471170927577843510~c5_720x720.webp?from=2634875926",
                        "https://p3.douyinpic.com/img/aweme-qrcode/BlsHiO7471170927577843510~c5_720x720.jpeg?from=2634875926"
                    ]
                },
                "trade_index": ""
            }
        ],
        "has_comp_permission": true,
        "main_industry": {
            "industry_id": 17,
            "industry_name": "虚拟充值"
        },
        "page_result": {
            "page_no": 9,
            "page_size": 10,
            "total": 200
        },
        "show_comp": true,
        "up_rank_num": 0,
        "version": 0
    },
    "msg": "",
    "st": 0
}